sqlalchemy_rqlite/__init__.py
sqlalchemy_rqlite/constants.py
sqlalchemy_rqlite/pyrqlite.py
sqlalchemy_rqlite-2.0.dist-info/LICENSE
sqlalchemy_rqlite-2.0.dist-info/METADATA
sqlalchemy_rqlite-2.0.dist-info/WHEEL
sqlalchemy_rqlite-2.0.dist-info/dependency_links.txt
sqlalchemy_rqlite-2.0.dist-info/entry_points.txt
sqlalchemy_rqlite-2.0.dist-info/top_level.txt
sqlalchemy_rqlite-2.0.dist-info/RECORD
