Metadata-Version: 2.1
Name: sqlalchemy_rqlite
Version: 2.0
Summary: SQLAlchemy dialect for rqlite
Author: Zac Medico
Author-email: zmedico@gmail.com
Maintainer: Zac Medico
Maintainer-email: zmedico@gmail.com
License: MIT
Keywords: rqlite SQLAlchemy
Platform: Posix
Classifier: Development Status :: 3 - Alpha
Classifier: Environment :: Console
Classifier: Intended Audience :: Developers
Classifier: License :: OSI Approved :: MIT License
Classifier: Programming Language :: Python
Classifier: Programming Language :: Python :: 2
Classifier: Programming Language :: Python :: 2.7
Classifier: Programming Language :: Python :: 3
Classifier: Programming Language :: Python :: 3.3
Classifier: Programming Language :: Python :: 3.4
Classifier: Programming Language :: Python :: 3.5
Classifier: Programming Language :: Python :: Implementation :: CPython
Classifier: Programming Language :: Python :: Implementation :: PyPy
Classifier: Topic :: Database :: Front-Ends
License-File: LICENSE
Requires-Dist: SQLAlchemy
Requires-Dist: pyrqlite
